examples/archive/aemo_2024_prog_manual.py
examples/archive/caiso_irp23_manual.py
examples/archive/nrel-118_manual.py
examples/archive/sem_2024_manual.py
plexos_to_pypsa_converter/__init__.py
plexos_to_pypsa_converter/analysis/__init__.py
plexos_to_pypsa_converter/analysis/benchmarking.py
plexos_to_pypsa_converter/analysis/core.py
plexos_to_pypsa_converter/analysis/metrics.py
plexos_to_pypsa_converter/analysis/plotting.py
plexos_to_pypsa_converter/analysis/reports.py
plexos_to_pypsa_converter/analysis/statistics.py
plexos_to_pypsa_converter/analysis/styles.py
plexos_to_pypsa_converter/analysis/utils.py
plexos_to_pypsa_converter/analysis/validation.py
plexos_to_pypsa_converter/analysis/visualizations.py
plexos_to_pypsa_converter/db/__init__.py
plexos_to_pypsa_converter/db/csv_readers.py
plexos_to_pypsa_converter/db/discovery.py
plexos_to_pypsa_converter/db/parse.py
plexos_to_pypsa_converter/db/rating.py
plexos_to_pypsa_converter/db/read.py
plexos_to_pypsa_converter/db/registry.py
plexos_to_pypsa_converter/db/timeslice_parser.py
plexos_to_pypsa_converter/examples/__init__.py
plexos_to_pypsa_converter/examples/aemo_2024_prog/aemo_2024_prog.py
plexos_to_pypsa_converter/examples/aemo_2024_prog/aemo_analysis.ipynb
plexos_to_pypsa_converter/examples/aemo_2024_prog/aemo_solve.ipynb
plexos_to_pypsa_converter/examples/caiso_irp23/caiso_analysis.ipynb
plexos_to_pypsa_converter/examples/caiso_irp23/caiso_irp23.py
plexos_to_pypsa_converter/examples/caiso_irp23/caiso_solve.ipynb
plexos_to_pypsa_converter/examples/nrel_118/nrel_118.py
plexos_to_pypsa_converter/examples/sem_2024_2032/sem_2024_2032.py
plexos_to_pypsa_converter/network/__init__.py
plexos_to_pypsa_converter/network/carriers_csv.py
plexos_to_pypsa_converter/network/conversion.py
plexos_to_pypsa_converter/network/core.py
plexos_to_pypsa_converter/network/core_csv.py
plexos_to_pypsa_converter/network/costs_csv.py
plexos_to_pypsa_converter/network/csv_loaders.py
plexos_to_pypsa_converter/network/generators_csv.py
plexos_to_pypsa_converter-0.1.0.dist-info/METADATA
plexos_to_pypsa_converter-0.1.0.dist-info/WHEEL
plexos_to_pypsa_converter-0.1.0.dist-info/top_level.txt
plexos_to_pypsa_converter-0.1.0.dist-info/RECORD
