Metadata-Version: 2.4
Name: plexos-to-pypsa-converter
Version: 0.1.0
Summary: PLEXOS-to-PyPSA Converter
Project-URL: Homepage, https://github.com/open-energy-transition/plexos-to-pypsa-converter
Project-URL: Source, https://github.com/open-energy-transition/plexos-to-pypsa-converter
Classifier: Programming Language :: Python :: 3.11
Classifier: Programming Language :: Python :: 3.12
Classifier: Environment :: Console
Classifier: Intended Audience :: Science/Research
Classifier: Natural Language :: English
Classifier: Operating System :: OS Independent
Classifier: Topic :: Scientific/Engineering
Requires-Python: >=3.11
Requires-Dist: pypsa<1.0,>=0.34
Requires-Dist: pandas>=2.2
Requires-Dist: numpy>=2.2
Requires-Dist: scipy>=1.15
Requires-Dist: xarray>=2025.1
Requires-Dist: netcdf4>=1.7
Requires-Dist: linopy>=0.5.5
Requires-Dist: matplotlib>=3.10
Requires-Dist: seaborn>=0.13
Requires-Dist: geopandas>=1.0
Requires-Dist: networkx>=3.4
Requires-Dist: pyyaml>=6.0
Requires-Dist: openpyxl>=3.1
Requires-Dist: tabulate>=0.9
Requires-Dist: deprecation
Requires-Dist: validators
Requires-Dist: plexosdb
Requires-Dist: rarfile>=4.0
Requires-Dist: requests>=2.31
Requires-Dist: tqdm>=4.66
Requires-Dist: plexos-coad-oet>=0.1.0
Provides-Extra: jupyter
Requires-Dist: jupyter>=1.0; extra == "jupyter"
Requires-Dist: ipykernel>=6.16; extra == "jupyter"
Requires-Dist: ipywidgets>=8.0; extra == "jupyter"
Requires-Dist: notebook>=6.5; extra == "jupyter"
Provides-Extra: solvers
Requires-Dist: gurobipy>=12.0; extra == "solvers"
Requires-Dist: highspy>=1.10; extra == "solvers"
Provides-Extra: test
Requires-Dist: pytest>=8.4; extra == "test"
Requires-Dist: pytest-cov>=6.0; extra == "test"
Requires-Dist: pytest-xdist>=3.6; extra == "test"
Requires-Dist: pytest-mock>=3.14; extra == "test"
Requires-Dist: hypothesis>=6.122; extra == "test"
Requires-Dist: faker>=33.1; extra == "test"
Provides-Extra: development
Requires-Dist: pytest>=8.4; extra == "development"
Requires-Dist: pytest-cov>=6.0; extra == "development"
Requires-Dist: pytest-xdist>=3.6; extra == "development"
Requires-Dist: pytest-mock>=3.14; extra == "development"
Requires-Dist: mypy>=1.15; extra == "development"
Requires-Dist: sphinx>=5.3; extra == "development"
Requires-Dist: sphinx-rtd-theme>=1.2; extra == "development"
Requires-Dist: numpydoc>=1.5; extra == "development"
Requires-Dist: pre-commit>=3.0; extra == "development"
Requires-Dist: ruff>=0.12; extra == "development"
